MANIFEST.in
README.md
setup.py
oauth2/__init__.py
oauth2/oauth2.py
requests_oauth2.egg-info/PKG-INFO
requests_oauth2.egg-info/SOURCES.txt
requests_oauth2.egg-info/dependency_links.txt
requests_oauth2.egg-info/not-zip-safe
requests_oauth2.egg-info/requires.txt
requests_oauth2.egg-info/top_level.txt