Metadata-Version: 1.0
Name: requests-oauth2
Version: 0.1.0
Summary: Open Authentication 2 support to Python-requests HTTP library.
Home-page: http://github.com/maraujop/requests-oauth2
Author: Miguel Araujo
Author-email: miguel.araujo.perez@gmail.com
License: BSD
Keywords: requests,python-requests,OAuth,open authentication
Platform: UNKNOWN
Classifier: Development Status :: 4 - Beta
Classifier: Intended Audience :: Developers
Classifier: Programming Language :: Python
Classifier: License :: OSI Approved :: BSD License
Classifier: Operating System :: OS Independent
Classifier: Topic :: Internet :: WWW/HTTP
Classifier: Topic :: Software Development :: Libraries :: Python Modules
